datadict_connector_dbt/__init__.py
datadict_connector_dbt/dbt.py
datadict_connector_dbt/dbt_applier.py
datadict_connector_dbt/dbt_keys.py
datadict_connector_dbt/dbt_loader.py
datadict_connector_dbt/dbt_path_builder.py
datadict_connector_dbt/dbt_schemas.py
datadict_connector_dbt/dbt_source.py
datadict_connector_dbt/dbt_types.py
datadict_connector_dbt-0.0.2.dist-info/METADATA
datadict_connector_dbt-0.0.2.dist-info/WHEEL
datadict_connector_dbt-0.0.2.dist-info/top_level.txt
datadict_connector_dbt-0.0.2.dist-info/RECORD
